functionStudio/CompositeFunction.py
functionStudio/__init__.py
functionStudio/functions.py
functionStudio/geneticAlgorithms.py
functionStudio/gpt2Function.py
functionStudio/neuralNetworkEstimator.py
functionStudio/utils.py
src/CompositeFunction.py
src/__init__.py
src/functions.py
src/geneticAlgorithms.py
src/gpt2Function.py
src/neuralNetworkEstimator.py
src/utils.py
FunctionStudio-0.0.3.dist-info/METADATA
FunctionStudio-0.0.3.dist-info/WHEEL
FunctionStudio-0.0.3.dist-info/top_level.txt
FunctionStudio-0.0.3.dist-info/RECORD
