Metadata-Version: 2.1
Name: FunctionStudio
Version: 0.0.3
Summary: Wrapper around evotorch to simplify any optimization task
Home-page: UNKNOWN
Author: Jasper Busschers
Author-email: jasperbu@gmail.com
License: UNKNOWN
Platform: UNKNOWN
Classifier: Programming Language :: Python :: 3
Classifier: License :: OSI Approved :: MIT License
Classifier: Operating System :: OS Independent
Requires-Python: >=3.9
Requires-Dist: evotorch (==0.5.1)
Requires-Dist: torch (==2.0.1)
